taskpods.py
taskpods-0.3.0.dist-info/licenses/LICENSE
taskpods-0.3.0.dist-info/METADATA
taskpods-0.3.0.dist-info/WHEEL
taskpods-0.3.0.dist-info/entry_points.txt
taskpods-0.3.0.dist-info/top_level.txt
taskpods-0.3.0.dist-info/RECORD
